LICENSE
MANIFEST.in
README.md
requirements.txt
setup.py
mapomatic/__init__.py
mapomatic/circuits.py
mapomatic/layouts.py
mapomatic/version.py
mapomatic.egg-info/PKG-INFO
mapomatic.egg-info/SOURCES.txt
mapomatic.egg-info/dependency_links.txt
mapomatic.egg-info/not-zip-safe
mapomatic.egg-info/requires.txt
mapomatic.egg-info/top_level.txt
mapomatic/tests/__init__.py
mapomatic/tests/test_best_layout.py
mapomatic/tests/test_best_layout_custom.py
mapomatic/tests/test_deflate_barriers.py
mapomatic/tests/test_inflate.py
mapomatic/tests/test_matching_layout.py
mapomatic/tests/test_subgraphs.py
mapomatic/tests/test_transpiler_layout.py